aiparo/__init__.py
aiparo/aiparo.py
aiparo-0.1.dist-info/METADATA
aiparo-0.1.dist-info/WHEEL
aiparo-0.1.dist-info/top_level.txt
aiparo-0.1.dist-info/RECORD
