Metadata-Version: 2.1
Name: aiparo
Version: 0.1
Requires-Dist: pyperclip
